LICENSE
README.md
setup.cfg
setup.py
./cval_lib/__init__.py
./cval_lib/api.py
./cval_lib/connection.py
./cval_lib/version.py
./cval_lib/configs/__init__.py
./cval_lib/configs/main_config.py
./cval_lib/examples/__init__.py
./cval_lib/examples/annotation.py
./cval_lib/examples/api.py
./cval_lib/examples/classification.py
./cval_lib/examples/dataset.py
./cval_lib/examples/detection.py
./cval_lib/examples/detection_entropy_multiclass.py
./cval_lib/examples/embeddings.py
./cval_lib/examples/embeddings_clustering.py
./cval_lib/examples/frames.py
./cval_lib/examples/method_combination.py
./cval_lib/examples/monkey_patch.py
./cval_lib/examples/on_pemise.py
./cval_lib/examples/polling.py
./cval_lib/examples/result.py
./cval_lib/examples/segmentation_annotation.py
./cval_lib/examples/storage.py
./cval_lib/handlers/__async.py
./cval_lib/handlers/__init__.py
./cval_lib/handlers/_abstract_handler.py
./cval_lib/handlers/_based_on_json.py
./cval_lib/handlers/annotation.py
./cval_lib/handlers/classification.py
./cval_lib/handlers/dataset.py
./cval_lib/handlers/detection.py
./cval_lib/handlers/embedding.py
./cval_lib/handlers/frame.py
./cval_lib/handlers/frames.py
./cval_lib/handlers/result.py
./cval_lib/handlers/segmentation.py
./cval_lib/handlers/storage.py
./cval_lib/handlers/weights.py
./cval_lib/models/__init__.py
./cval_lib/models/_base.py
./cval_lib/models/annotation.py
./cval_lib/models/classification.py
./cval_lib/models/dataset.py
./cval_lib/models/detection.py
./cval_lib/models/embedding.py
./cval_lib/models/frame.py
./cval_lib/models/queue.py
./cval_lib/models/result.py
./cval_lib/models/storage.py
./cval_lib/models/weights.py
./cval_lib/patterns/__init__.py
./cval_lib/patterns/singleton.py
./cval_lib/tools/__init__.py
./cval_lib/tools/annotation.py
./cval_lib/tools/convert.py
./cval_lib/tools/get_embeddings.py
./cval_lib/utils/__init__.py
./cval_lib/utils/base_conn.py
./cval_lib/utils/entrypoint.py
./cval_lib/utils/exceptions.py
./cval_lib/utils/install_dynamically.py
cval_lib.egg-info/PKG-INFO
cval_lib.egg-info/SOURCES.txt
cval_lib.egg-info/dependency_links.txt
cval_lib.egg-info/requires.txt
cval_lib.egg-info/top_level.txt
